Workbook

Sheet 前提条件
A1: RANDISH 原価試算 — 前提条件
A2: 青字＝入力セル（自由に変更してください）／黒字＝計算式。数値を変えると全シートが再計算されます。
A3: 作成日: 2026-08-02
A5: 項目 | B5: 値 | C5: 単位 | D5: 根拠・メモ
A6: 為替レート（USD→JPY） | B6: 157.64 | C6: 円/$ | D6: 2026-08-02 時点の仲値。xe.com。ドル建てAPI費用の換算に使用
A8: ■ 利用者の行動（1人あたり月間） | D8: ここが原価を決める最大の要因。実測が取れたら差し替えてください
A9: 月間セッション数 | B9: 8 | C9: 回/月 | D9: 仮定値。アプリを開いて条件を触る一連の操作を1セッションとする
A10: 1セッションの条件変更回数 | B10: 3 | C10: 回 | D10: 仮定値。エリア・ジャンル・予算・距離のいずれかを変えた回数
A11: 1セッションの抽選回数 | B11: 2 | C11: 回 | D11: 仮定値。食券が1日4枚なので上限まで使う想定ではない
A12: 1セッションで表示される写真枚数 | B12: 12 | C12: 枚 | D12: 仮定値。候補カードをスクロールして目に入る枚数
A13: AIレポート生成回数 | B13: 1 | C13: 回/月 | D13: 月1回の設計どおり
A15: ■ 1回の操作で飛ぶGoogle検索回数（コードから確定）
A16: 候補一覧1回あたりのText Search | B16: 4 | C16: 回 | D16: GooglePlacesEnrichmentService: ジャンル指定時3キーワード・すべて選択時5キーワードを個別に検索。平均4で計算
A17: 抽選1回あたりのText Search | B17: 1 | C17: 回 | D17: NearbyPlacesService.searchNearbyCandidates は reserveGoogleRequests(1)。1リクエスト固定
A18: 写真1枚あたりのPhotoリクエスト | B18: 1 | C18: 回 | D18: GooglePlacesEnrichmentService.fetchPhoto は Cache-Control: no-store。表示のたびに課金される
A20: ■ AIレポート1回のトークン数
A21: 入力トークン | B21: 1500 | C21: token | D21: 推定値。プロンプト本文＋分析JSON。実測してください
A22: 出力トークン | B22: 800 | C22: token | D22: 推定値。maxOutputTokens は 4096 だが実際の出力はこの程度
A25: ■ 収益の前提
A26: 月額サブスク価格 | B26: 400 | C26: 円/月 | D26: 税込。RevenueCat 経由
A27: 課金率（有料転換率） | B27: 0.03 | C27: % | D27: 仮定値。個人向けアプリの一般的な水準は1〜5%
A28: 決済手数料率 | B28: 0.3 | C28: % | D28: App Store / Google Play は30%（小規模事業者プログラムなら15%）。Web決済なら3.6%程度
A29: 広告ARPU（無料ユーザー1人あたり） | B29: 15 | C29: 円/月 | D29: 仮定値。バナー中心の場合の目安。実績が出たら差し替え

Sheet API単価
A1: API・インフラ単価（2026年8月時点の公式価格）
A2: 出典: Google Maps Platform 価格表（最終更新 2026-07-20）／Gemini API 価格表／各社公式
A4: サービス | B4: SKU / プラン | C4: 無料枠（月） | D4: 超過後の単価 | E4: 単位 | F4: 備考
A5: Google Places | B5: Text Search Pro | C5: 5000 | D5: 32 | E5: $/1,000回 | F5: 候補一覧と抽選で使用。RANDISHの最大のコスト要因
A6: Google Places | B6: Place Details Photos | C6: 1000 | D6: 7 | E6: $/1,000回 | F6: 店舗写真。no-storeのため表示ごとに課金
A7: Google Maps | B7: Maps Embed API | C7: — | D7: 0 | E7: $ | F7: 無制限で無料。Webの地図はこれを使用（コスト0）
A8: Google Maps | B8: Dynamic Maps (SDK) | C8: — | D8: 0 | E8: $ | F8: iOS/Android SDKの地図表示は無料（Maps SDK）
A9: Gemini | B9: 2.5 Flash 入力 | C9: — | D9: 0.3 | E9: $/100万token | F9: AIレポート生成
A10: Gemini | B10: 2.5 Flash 出力 | C10: — | D10: 2.5 | E10: $/100万token | F10: 思考トークン込み。thinkingBudget=0で抑制済み
A11: Gemini | B11: 2.5 Flash-Lite 入力 | C11: — | D11: 0.1 | E11: $/100万token | F11: 代替案。Flashの1/3
A12: Gemini | B12: 2.5 Flash-Lite 出力 | C12: — | D12: 0.4 | E12: $/100万token | F12: 代替案。Flashの1/6
A13: HotPepper | B13: グルメサーチAPI | C13: — | D13: 0 | E13: 円 | F13: 無料。写真つきで返るためGoogleの代替になる
A14: Geoapify | B14: Places API | C14: — | D14: 0 | E14: 円 | F14: 無料枠内で運用中。写真は返らない
A17: ■ 固定費（月額）
A18: サービス | B18: プラン | C18: 月額(USD) | D18: 月額(円) | F18: 備考
A19: Render | B19: Starter (512MB) | C19: 7 | D19: =C19*前提条件!$B$6 -> 1103.48 | F19: コールドスタート63秒を解消するために必須。無料枠だと初回が必ず遅い
A20: Supabase | B20: Free | C20: 0 | D20: =C20*前提条件!$B$6 -> 0 | F20: 無料枠で 50,000 MAU・DB 500MB まで。7日間無操作で停止する点に注意
A21: Vercel | B21: Hobby | C21: 0 | D21: =C21*前提条件!$B$6 -> 0 | F21: 個人利用は無料。収益化すると規約上 Pro($20/月) が必要になる
A22: Resend | B22: Free | C22: 0 | D22: =C22*前提条件!$B$6 -> 0 | F22: 認証コード送信。無料枠の上限は要確認
A23: 固定費 合計 | C23: =SUM(C19:C22) -> 7 | D23: =SUM(D19:D22) -> 1103.48

Sheet 1人あたり原価
A1: 利用者1人あたりの月間原価
A2: 無料枠は「サービス全体の月間上限」なので、ここでは無料枠を使い切った後の限界原価として計算しています。
A4: 項目 | B4: 計算式 | C4: 回数/月 | D4: 単価(USD) | E4: 原価(USD) | F4: 原価(円)
A5: Google Text Search（候補一覧） | B5: セッション × 条件変更 × キーワード数 | C5: =前提条件!B9*前提条件!B10*前提条件!B16 -> 96 | D5: =API単価!D5/1000 -> 0.032 | E5: =C5*D5 -> 3.072 | F5: =E5*前提条件!$B$6 -> 484.27008
A6: Google Text Search（抽選） | B6: セッション × 抽選回数 × 1 | C6: =前提条件!B9*前提条件!B11*前提条件!B17 -> 16 | D6: =API単価!D5/1000 -> 0.032 | E6: =C6*D6 -> 0.512 | F6: =E6*前提条件!$B$6 -> 80.71168
A7: Google 店舗写真 | B7: セッション × 表示枚数（キャッシュ無し） | C7: =前提条件!B9*前提条件!B12*前提条件!B18 -> 96 | D7: =API単価!D6/1000 -> 0.007 | E7: =C7*D7 -> 0.672 | F7: =E7*前提条件!$B$6 -> 105.93408
A8: Gemini AIレポート | B8: (入力token×単価 + 出力token×単価) × 回数 | C8: =前提条件!B13 -> 1 | D8: =(前提条件!B21*API単価!D9+前提条件!B22*API単価!D10)/1000000 -> 0.00245 | E8: =C8*D8 -> 0.00245 | F8: =E8*前提条件!$B$6 -> 0.386218
A10: 1人あたり月間原価 合計 | E10: =SUM(E5:E8) -> 4.25845 | F10: =SUM(F5:F8) -> 671.30206
A12: ■ 損益分岐の確認
A14: サブスク収入（1人・手数料後） | B14: =前提条件!B26*(1-前提条件!B28) -> 280
A15: 1人あたり原価（上の合計） | B15: =F10 -> 671.30206
A16: 差引（有料ユーザー1人あたり） | B16: =B14-B15 -> -391.30206 | D16: ← マイナスなら、課金するほど赤字が増えるという意味
A17: 原価を賄うのに必要な月額 | B17: =F10/(1-前提条件!B28) -> 959.00294 | D17: ← 現状の使い方を変えないまま黒字にするなら、この価格が必要

Sheet 月次収支
A1: 規模別の月次収支シミュレーション
A2: MAU（月間利用者数）を変えたときの収入・原価・利益。無料枠は全体に一度だけ効くため考慮済み。
A4: MAU | B4: 有料 ユーザー数 | C4: サブスク収入 (手数料後) | D4: 広告収入 | E4: 収入合計 | F4: Google検索 回数 | G4: Google写真 回数 | H4: 変動原価 | I4: 固定費 | J4: 原価合計 | K4: 営業利益 | L4: 1人あたり 利益
A5: 100 | B5: =A5*前提条件!$B$27 -> 3 | C5: =B5*前提条件!$B$26*(1-前提条件!$B$28) -> 840 | D5: =(A5-B5)*前提条件!$B$29 -> 1455 | E5: =C5+D5 -> 2295 | F5: =A5*('1人あたり原価'!$C$5+'1人あたり原価'!$C$6) -> 11200 | G5: =A5*'1人あたり原価'!$C$7 -> 9600 | H5: =(MAX(0,F5-API単価!$C$5)*API単価!$D$5/1000+MAX(0,G5-API単価!$C$6)*API単価!$D$6/1000+A5*'1人あたり原価'!$E$8)*前提条件!$B$6 -> 40804.326 | I5: =API単価!$D$23 -> 1103.48 | J5: =H5+I5 -> 41907.806 | K5: =E5-J5 -> -39612.806 | L5: =IF(A5=0,0,K5/A5) -> -396.12806
A6: 500 | B6: =A6*前提条件!$B$27 -> 15 | C6: =B6*前提条件!$B$26*(1-前提条件!$B$28) -> 4200 | D6: =(A6-B6)*前提条件!$B$29 -> 7275 | E6: =C6+D6 -> 11475 | F6: =A6*('1人あたり原価'!$C$5+'1人あたり原価'!$C$6) -> 56000 | G6: =A6*'1人あたり原価'!$C$7 -> 48000 | H6: =(MAX(0,F6-API単価!$C$5)*API単価!$D$5/1000+MAX(0,G6-API単価!$C$6)*API単価!$D$6/1000+A6*'1人あたり原価'!$E$8)*前提条件!$B$6 -> 309325.15 | I6: =API単価!$D$23 -> 1103.48 | J6: =H6+I6 -> 310428.63 | K6: =E6-J6 -> -298953.63 | L6: =IF(A6=0,0,K6/A6) -> -597.90726
A7: 1000 | B7: =A7*前提条件!$B$27 -> 30 | C7: =B7*前提条件!$B$26*(1-前提条件!$B$28) -> 8400 | D7: =(A7-B7)*前提条件!$B$29 -> 14550 | E7: =C7+D7 -> 22950 | F7: =A7*('1人あたり原価'!$C$5+'1人あたり原価'!$C$6) -> 112000 | G7: =A7*'1人あたり原価'!$C$7 -> 96000 | H7: =(MAX(0,F7-API単価!$C$5)*API単価!$D$5/1000+MAX(0,G7-API単価!$C$6)*API単価!$D$6/1000+A7*'1人あたり原価'!$E$8)*前提条件!$B$6 -> 644976.18 | I7: =API単価!$D$23 -> 1103.48 | J7: =H7+I7 -> 646079.66 | K7: =E7-J7 -> -623129.66 | L7: =IF(A7=0,0,K7/A7) -> -623.12966
A8: 5000 | B8: =A8*前提条件!$B$27 -> 150 | C8: =B8*前提条件!$B$26*(1-前提条件!$B$28) -> 42000 | D8: =(A8-B8)*前提条件!$B$29 -> 72750 | E8: =C8+D8 -> 114750 | F8: =A8*('1人あたり原価'!$C$5+'1人あたり原価'!$C$6) -> 560000 | G8: =A8*'1人あたり原価'!$C$7 -> 480000 | H8: =(MAX(0,F8-API単価!$C$5)*API単価!$D$5/1000+MAX(0,G8-API単価!$C$6)*API単価!$D$6/1000+A8*'1人あたり原価'!$E$8)*前提条件!$B$6 -> 3330184.4 | I8: =API単価!$D$23 -> 1103.48 | J8: =H8+I8 -> 3331287.9 | K8: =E8-J8 -> -3216537.9 | L8: =IF(A8=0,0,K8/A8) -> -643.30758
A9: 10000 | B9: =A9*前提条件!$B$27 -> 300 | C9: =B9*前提条件!$B$26*(1-前提条件!$B$28) -> 84000 | D9: =(A9-B9)*前提条件!$B$29 -> 145500 | E9: =C9+D9 -> 229500 | F9: =A9*('1人あたり原価'!$C$5+'1人あたり原価'!$C$6) -> 1120000 | G9: =A9*'1人あたり原価'!$C$7 -> 960000 | H9: =(MAX(0,F9-API単価!$C$5)*API単価!$D$5/1000+MAX(0,G9-API単価!$C$6)*API単価!$D$6/1000+A9*'1人あたり原価'!$E$8)*前提条件!$B$6 -> 6686694.7 | I9: =API単価!$D$23 -> 1103.48 | J9: =H9+I9 -> 6687798.2 | K9: =E9-J9 -> -6458298.2 | L9: =IF(A9=0,0,K9/A9) -> -645.82982
A10: 50000 | B10: =A10*前提条件!$B$27 -> 1500 | C10: =B10*前提条件!$B$26*(1-前提条件!$B$28) -> 420000 | D10: =(A10-B10)*前提条件!$B$29 -> 727500 | E10: =C10+D10 -> 1147500 | F10: =A10*('1人あたり原価'!$C$5+'1人あたり原価'!$C$6) -> 5600000 | G10: =A10*'1人あたり原価'!$C$7 -> 4800000 | H10: =(MAX(0,F10-API単価!$C$5)*API単価!$D$5/1000+MAX(0,G10-API単価!$C$6)*API単価!$D$6/1000+A10*'1人あたり原価'!$E$8)*前提条件!$B$6 -> 33538777 | I10: =API単価!$D$23 -> 1103.48 | J10: =H10+I10 -> 33539880 | K10: =E10-J10 -> -32392380 | L10: =IF(A10=0,0,K10/A10) -> -647.84761
A13: 読み方: 「営業利益」がマイナスなら、その規模では使えば使うほど赤字。MAUを増やしても改善しないなら構造の問題です。

Sheet 削減施策
A1: 原価を下げる施策と効果（コードの実態にもとづく）
A2: 削減率は現状のコードから見積もった概算です。実装後に実測で更新してください。
A4: # | B4: 施策 | C4: 現状の問題 | D4: 想定削減率 | E4: 実装難易度 | F4: 備考
A5: 1 | B5: 写真をキャッシュする | C5: fetchPhoto が Cache-Control: no-store。同じ店の写真を見るたびに課金される | D5: 0.85 | E5: 低 | F5: CDN or サーバー側で24時間キャッシュするだけ。写真costの大半が消える
A6: 2 | B6: 候補一覧のGoogle検索をやめる | C6: 一覧の取得で3〜5キーワードを個別にText Search。1回の条件変更で最大5リクエスト | D6: 0.75 | E6: 中 | F6: HotPepper優先で足りることが検証済み。Googleは件数不足時のみに限定する
A7: 3 | B7: nearbyのキャッシュを復活させる | C7: Google有効時に findCacheEntry を丸ごとスキップしている（キャッシュ無効） | D7: 0.4 | E7: 低 | F7: NearbyPlacesService の1行。同一条件の連打が全部課金されている
A8: 4 | B8: 条件変更のたびに検索しない | C8: useEffect が条件変更ごとに loadRestaurants を発火。デバウンス無し | D8: 0.5 | E8: 低 | F8: 500ms のデバウンス、または「この条件で探す」ボタン方式にする
A9: 5 | B9: AIレポートをFlash-Liteにする | C9: Flash($2.50/M出力) → Flash-Lite($0.40/M出力) | D9: 0.84 | E9: 低 | F9: ただし元々ほぼ0円なので、効果は誤差。品質を優先してFlashのままで良い
A10: 6 | B10: 写真はHotPepper優先 | C10: HotPepperは無料で写真つき。Googleの写真を使う場面を減らす | D10: 0.5 | E10: 低 | F10: 既に統合済みの仕組みを使う。表示順で優先するだけ
A13: ■ 施策1〜4を実施した場合の1人あたり原価
A14: 現状の1人あたり原価 | B14: ='1人あたり原価'!F10 -> 671.30206
A15: 検索コスト（施策2・3・4適用後） | B15: =('1人あたり原価'!F5+'1人あたり原価'!F6)*(1-D6)*(1-D7)*(1-D8) -> 42.373632
A16: 写真コスト（施策1適用後） | B16: ='1人あたり原価'!F7*(1-D5) -> 15.890112
A17: AIレポート | B17: ='1人あたり原価'!F8 -> 0.386218
A18: 改善後の1人あたり原価 | B18: =B15+B16+B17 -> 58.649962
A19: サブスク収入（1人・手数料後） | B19: =前提条件!B26*(1-前提条件!B28) -> 280
A20: 改善後の差引 | B20: =B19-B18 -> 221.35004 | D20: ← プラスになれば、月額400円で成立する
